{"otherData": {},"traceEvents":[{"cat":"function","dur":121375,"name":"Pistachio::WindowsWindow::Init","ph":"X","pid":0,"tid":3648595959,"ts":68135185885},{"cat":"function","dur":1644925,"name":"Pistachio::DX11RendererBase::CreateDevice","ph":"X","pid":0,"tid":3648595959,"ts":68135315162},{"cat":"function","dur":8073,"name":"Pistachio::RendererBase::Resize","ph":"X","pid":0,"tid":3648595959,"ts":68136961178},{"cat":"function","dur":1654477,"name":"Pistachio::RendererBase::Init","ph":"X","pid":0,"tid":3648595959,"ts":68135315156},{"cat":"function","dur":348,"name":"Pistachio::ConstantBuffer::Create","ph":"X","pid":0,"tid":3648595959,"ts":68136969919},{"cat":"function","dur":82,"name":"Pistachio::ConstantBuffer::Create","ph":"X","pid":0,"tid":3648595959,"ts":68136970312},{"cat":"function","dur":74,"name":"Pistachio::ConstantBuffer::Create","ph":"X","pid":0,"tid":3648595959,"ts":68136970430},{"cat":"function","dur":840,"name":"Pistachio::Renderer::CreateConstantBuffers","ph":"X","pid":0,"tid":3648595959,"ts":68136969687},{"cat":"function","dur":11,"name":"Pistachio::ConstantBuffer::Create","ph":"X","pid":0,"tid":3648595959,"ts":68136970565},{"cat":"function","dur":108974,"name":"stbi_loadf","ph":"X","pid":0,"tid":3648595959,"ts":68136971179},{"cat":"function","dur":10670,"name":"Pistachio::Texture2D::CreateTexture","ph":"X","pid":0,"tid":3648595959,"ts":68137080616},{"cat":"function","dur":121251,"name":"Pistachio::Texture2D::CreateStack","ph":"X","pid":0,"tid":3648595959,"ts":68136971179},{"cat":"function","dur":2412,"name":"Pistachio::PixelShader::PixelShader","ph":"X","pid":0,"tid":3648595959,"ts":68137092712},{"cat":"function","dur":602,"name":"Pistachio::VertexShader::VertexShader","ph":"X","pid":0,"tid":3648595959,"ts":68137095211},{"cat":"function","dur":320,"name":"Pistachio::PixelShader::PixelShader","ph":"X","pid":0,"tid":3648595959,"ts":68137095853},{"cat":"function","dur":160,"name":"Pistachio::VertexShader::VertexShader","ph":"X","pid":0,"tid":3648595959,"ts":68137096206},{"cat":"function","dur":614,"name":"Pistachio::PixelShader::PixelShader","ph":"X","pid":0,"tid":3648595959,"ts":68137096394},{"cat":"function","dur":295,"name":"Pistachio::VertexShader::VertexShader","ph":"X","pid":0,"tid":3648595959,"ts":68137097043},{"cat":"function","dur":486,"name":"Pistachio::PixelShader::PixelShader","ph":"X","pid":0,"tid":3648595959,"ts":68137097371},{"cat":"function","dur":400,"name":"Pistachio::VertexShader::VertexShader","ph":"X","pid":0,"tid":3648595959,"ts":68137097891},{"cat":"function","dur":76,"name":"Pistachio::Shader::CreateLayout","ph":"X","pid":0,"tid":3648595959,"ts":68137098328},{"cat":"function","dur":55,"name":"Pistachio::Shader::CreateLayout","ph":"X","pid":0,"tid":3648595959,"ts":68137098428},{"cat":"function","dur":54,"name":"Pistachio::Shader::CreateLayout","ph":"X","pid":0,"tid":3648595959,"ts":68137098504},{"cat":"function","dur":57,"name":"Pistachio::Shader::CreateLayout","ph":"X","pid":0,"tid":3648595959,"ts":68137098579},{"cat":"function","dur":330,"name":"Pistachio::VertexBuffer::CreateStack","ph":"X","pid":0,"tid":3648595959,"ts":68137157298},{"cat":"function","dur":162,"name":"Pistachio::IndexBuffer::CreateStack","ph":"X","pid":0,"tid":3648595959,"ts":68137157838},{"cat":"function","dur":67724,"name":"Pistachio::Mesh::CreateStack","ph":"X","pid":0,"tid":3648595959,"ts":68137098664},{"cat":"function","dur":74,"name":"Pistachio::VertexBuffer::CreateStack","ph":"X","pid":0,"tid":3648595959,"ts":68137184474},{"cat":"function","dur":18,"name":"Pistachio::IndexBuffer::CreateStack","ph":"X","pid":0,"tid":3648595959,"ts":68137184622},{"cat":"function","dur":18348,"name":"Pistachio::Mesh::CreateStack","ph":"X","pid":0,"tid":3648595959,"ts":68137166472},{"cat":"function","dur":1027,"name":"Pistachio::RenderCubeMap::CreateStack","ph":"X","pid":0,"tid":3648595959,"ts":68137184850},{"cat":"function","dur":7,"name":"Pistachio::Shader::Bind","ph":"X","pid":0,"tid":3648595959,"ts":68137186372},{"cat":"function","dur":2,"name":"Pistachio::Shader::Bind","ph":"X","pid":0,"tid":3648595959,"ts":68137186406},{"cat":"function","dur":5,"name":"Pistachio::Texture2D::Bind","ph":"X","pid":0,"tid":3648595959,"ts":68137186425},{"cat":"function","dur":4,"name":"Pistachio::RenderCubeMap::Bind","ph":"X","pid":0,"tid":3648595959,"ts":68137186504},{"cat":"function","dur":5,"name":"Pistachio::RenderCubeMap::Clear","ph":"X","pid":0,"tid":3648595959,"ts":68137186528},{"cat":"function","dur":14,"name":"Pistachio::ConstantBuffer::Update","ph":"X","pid":0,"tid":3648595959,"ts":68137186555},{"cat":"function","dur":5,"name":"Pistachio::Shader::SetVSBuffer","ph":"X","pid":0,"tid":3648595959,"ts":68137186587},{"cat":"function","dur":184,"name":"Pistachio::VertexBuffer::Bind","ph":"X","pid":0,"tid":3648595959,"ts":68137186608},{"cat":"function","dur":418,"name":"Pistachio::IndexBuffer::Bind","ph":"X","pid":0,"tid":3648595959,"ts":68137186816},{"cat":"function","dur":2,"name":"Pistachio::RenderCubeMap::Bind","ph":"X","pid":0,"tid":3648595959,"ts":68137187716},{"cat":"function","dur":1,"name":"Pistachio::RenderCubeMap::Clear","ph":"X","pid":0,"tid":3648595959,"ts":68137187745},{"cat":"function","dur":6,"name":"Pistachio::ConstantBuffer::Update","ph":"X","pid":0,"tid":3648595959,"ts":68137187763},{"cat":"function","dur":1,"name":"Pistachio::Shader::SetVSBuffer","ph":"X","pid":0,"tid":3648595959,"ts":68137187786},{"cat":"function","dur":1,"name":"Pistachio::VertexBuffer::Bind","ph":"X","pid":0,"tid":3648595959,"ts":68137187803},{"cat":"function","dur":1,"name":"Pistachio::IndexBuffer::Bind","ph":"X","pid":0,"tid":3648595959,"ts":68137187820},{"cat":"function","dur":1,"name":"Pistachio::RenderCubeMap::Bind","ph":"X","pid":0,"tid":3648595959,"ts":68137187839},{"cat":"function","dur":1,"name":"Pistachio::RenderCubeMap::Clear","ph":"X","pid":0,"tid":3648595959,"ts":68137187856},{"cat":"function","dur":2,"name":"Pistachio::ConstantBuffer::Update","ph":"X","pid":0,"tid":3648595959,"ts":68137187872},{"cat":"function","dur":1,"name":"Pistachio::Shader::SetVSBuffer","ph":"X","pid":0,"tid":3648595959,"ts":68137187889},{"cat":"function","dur":0,"name":"Pistachio::VertexBuffer::Bind","ph":"X","pid":0,"tid":3648595959,"ts":68137187909},{"cat":"function","dur":1,"name":"Pistachio::IndexBuffer::Bind","ph":"X","pid":0,"tid":3648595959,"ts":68137187924},{"cat":"function","dur":1,"name":"Pistachio::RenderCubeMap::Bind","ph":"X","pid":0,"tid":3648595959,"ts":68137187942},{"cat":"function","dur":0,"name":"Pistachio::RenderCubeMap::Clear","ph":"X","pid":0,"tid":3648595959,"ts":68137187959},{"cat":"function","dur":2,"name":"Pistachio::ConstantBuffer::Update","ph":"X","pid":0,"tid":3648595959,"ts":68137187974},{"cat":"function","dur":0,"name":"Pistachio::Shader::SetVSBuffer","ph":"X","pid":0,"tid":3648595959,"ts":68137187992},{"cat":"function","dur":1,"name":"Pistachio::VertexBuffer::Bind","ph":"X","pid":0,"tid":3648595959,"ts":68137188007},{"cat":"function","dur":0,"name":"Pistachio::IndexBuffer::Bind","ph":"X","pid":0,"tid":3648595959,"ts":68137188023},{"cat":"function","dur":1,"name":"Pistachio::RenderCubeMap::Bind","ph":"X","pid":0,"tid":3648595959,"ts":68137188040},{"cat":"function","dur":0,"name":"Pistachio::RenderCubeMap::Clear","ph":"X","pid":0,"tid":3648595959,"ts":68137188057},{"cat":"function","dur":10,"name":"Pistachio::ConstantBuffer::Update","ph":"X","pid":0,"tid":3648595959,"ts":68137188073},{"cat":"function","dur":0,"name":"Pistachio::Shader::SetVSBuffer","ph":"X","pid":0,"tid":3648595959,"ts":68137188099},{"cat":"function","dur":1,"name":"Pistachio::VertexBuffer::Bind","ph":"X","pid":0,"tid":3648595959,"ts":68137188114},{"cat":"function","dur":0,"name":"Pistachio::IndexBuffer::Bind","ph":"X","pid":0,"tid":3648595959,"ts":68137188130},{"cat":"function","dur":1,"name":"Pistachio::RenderCubeMap::Bind","ph":"X","pid":0,"tid":3648595959,"ts":68137188148},{"cat":"function","dur":0,"name":"Pistachio::RenderCubeMap::Clear","ph":"X","pid":0,"tid":3648595959,"ts":68137188165},{"cat":"function","dur":1,"name":"Pistachio::ConstantBuffer::Update","ph":"X","pid":0,"tid":3648595959,"ts":68137188184},{"cat":"function","dur":0,"name":"Pistachio::Shader::SetVSBuffer","ph":"X","pid":0,"tid":3648595959,"ts":68137188201},{"cat":"function","dur":1,"name":"Pistachio::VertexBuffer::Bind","ph":"X","pid":0,"tid":3648595959,"ts":68137188234},{"cat":"function","dur":0,"name":"Pistachio::IndexBuffer::Bind","ph":"X","pid":0,"tid":3648595959,"ts":68137188251},{"cat":"function","dur":0,"name":"Pistachio::RenderCubeMap::GetID","ph":"X","pid":0,"tid":3648595959,"ts":68137188269},{"cat":"function","dur":248,"name":"Pistachio::RenderCubeMap::CreateStack","ph":"X","pid":0,"tid":3648595959,"ts":68137188290},{"cat":"function","dur":1,"name":"Pistachio::Shader::Bind","ph":"X","pid":0,"tid":3648595959,"ts":68137188587},{"cat":"function","dur":1,"name":"Pistachio::Shader::Bind","ph":"X","pid":0,"tid":3648595959,"ts":68137188605},{"cat":"function","dur":2,"name":"Pistachio::RenderCubeMap::Bind","ph":"X","pid":0,"tid":3648595959,"ts":68137188621},{"cat":"function","dur":1,"name":"Pistachio::RenderCubeMap::Clear","ph":"X","pid":0,"tid":3648595959,"ts":68137188638},{"cat":"function","dur":5,"name":"Pistachio::ConstantBuffer::Update","ph":"X","pid":0,"tid":3648595959,"ts":68137188654},{"cat":"function","dur":1,"name":"Pistachio::Shader::SetVSBuffer","ph":"X","pid":0,"tid":3648595959,"ts":68137188675},{"cat":"function","dur":1,"name":"Pistachio::RenderCubeMap::BindResource","ph":"X","pid":0,"tid":3648595959,"ts":68137188691},{"cat":"function","dur":1,"name":"Pistachio::VertexBuffer::Bind","ph":"X","pid":0,"tid":3648595959,"ts":68137188708},{"cat":"function","dur":1,"name":"Pistachio::IndexBuffer::Bind","ph":"X","pid":0,"tid":3648595959,"ts":68137188724},{"cat":"function","dur":0,"name":"Pistachio::RenderCubeMap::Bind","ph":"X","pid":0,"tid":3648595959,"ts":68137188747},{"cat":"function","dur":1,"name":"Pistachio::RenderCubeMap::Clear","ph":"X","pid":0,"tid":3648595959,"ts":68137188763},{"cat":"function","dur":2,"name":"Pistachio::ConstantBuffer::Update","ph":"X","pid":0,"tid":3648595959,"ts":68137188779},{"cat":"function","dur":0,"name":"Pistachio::Shader::SetVSBuffer","ph":"X","pid":0,"tid":3648595959,"ts":68137188797},{"cat":"function","dur":1,"name":"Pistachio::RenderCubeMap::BindResource","ph":"X","pid":0,"tid":3648595959,"ts":68137188812},{"cat":"function","dur":1,"name":"Pistachio::VertexBuffer::Bind","ph":"X","pid":0,"tid":3648595959,"ts":68137188828},{"cat":"function","dur":1,"name":"Pistachio::IndexBuffer::Bind","ph":"X","pid":0,"tid":3648595959,"ts":68137188844},{"cat":"function","dur":1,"name":"Pistachio::RenderCubeMap::Bind","ph":"X","pid":0,"tid":3648595959,"ts":68137188862},{"cat":"function","dur":0,"name":"Pistachio::RenderCubeMap::Clear","ph":"X","pid":0,"tid":3648595959,"ts":68137188879},{"cat":"function","dur":3,"name":"Pistachio::ConstantBuffer::Update","ph":"X","pid":0,"tid":3648595959,"ts":68137188954},{"cat":"function","dur":3,"name":"Pistachio::Shader::SetVSBuffer","ph":"X","pid":0,"tid":3648595959,"ts":68137188982},{"cat":"function","dur":1,"name":"Pistachio::RenderCubeMap::BindResource","ph":"X","pid":0,"tid":3648595959,"ts":68137189008},{"cat":"function","dur":0,"name":"Pistachio::VertexBuffer::Bind","ph":"X","pid":0,"tid":3648595959,"ts":68137189033},{"cat":"function","dur":1,"name":"Pistachio::IndexBuffer::Bind","ph":"X","pid":0,"tid":3648595959,"ts":68137189060},{"cat":"function","dur":2,"name":"Pistachio::RenderCubeMap::Bind","ph":"X","pid":0,"tid":3648595959,"ts":68137189088},{"cat":"function","dur":0,"name":"Pistachio::RenderCubeMap::Clear","ph":"X","pid":0,"tid":3648595959,"ts":68137189115},{"cat":"function","dur":3,"name":"Pistachio::ConstantBuffer::Update","ph":"X","pid":0,"tid":3648595959,"ts":68137189134},{"cat":"function","dur":1,"name":"Pistachio::Shader::SetVSBuffer","ph":"X","pid":0,"tid":3648595959,"ts":68137189160},{"cat":"function","dur":1,"name":"Pistachio::RenderCubeMap::BindResource","ph":"X","pid":0,"tid":3648595959,"ts":68137189184},{"cat":"function","dur":1,"name":"Pistachio::VertexBuffer::Bind","ph":"X","pid":0,"tid":3648595959,"ts":68137189209},{"cat":"function","dur":1,"name":"Pistachio::IndexBuffer::Bind","ph":"X","pid":0,"tid":3648595959,"ts":68137189236},{"cat":"function","dur":1,"name":"Pistachio::RenderCubeMap::Bind","ph":"X","pid":0,"tid":3648595959,"ts":68137189267},{"cat":"function","dur":1,"name":"Pistachio::RenderCubeMap::Clear","ph":"X","pid":0,"tid":3648595959,"ts":68137189292},{"cat":"function","dur":7,"name":"Pistachio::ConstantBuffer::Update","ph":"X","pid":0,"tid":3648595959,"ts":68137189314},{"cat":"function","dur":1,"name":"Pistachio::Shader::SetVSBuffer","ph":"X","pid":0,"tid":3648595959,"ts":68137189342},{"cat":"function","dur":1,"name":"Pistachio::RenderCubeMap::BindResource","ph":"X","pid":0,"tid":3648595959,"ts":68137189363},{"cat":"function","dur":1,"name":"Pistachio::VertexBuffer::Bind","ph":"X","pid":0,"tid":3648595959,"ts":68137189383},{"cat":"function","dur":1,"name":"Pistachio::IndexBuffer::Bind","ph":"X","pid":0,"tid":3648595959,"ts":68137189400},{"cat":"function","dur":2,"name":"Pistachio::RenderCubeMap::Bind","ph":"X","pid":0,"tid":3648595959,"ts":68137189422},{"cat":"function","dur":0,"name":"Pistachio::RenderCubeMap::Clear","ph":"X","pid":0,"tid":3648595959,"ts":68137189441},{"cat":"function","dur":3,"name":"Pistachio::ConstantBuffer::Update","ph":"X","pid":0,"tid":3648595959,"ts":68137189458},{"cat":"function","dur":1,"name":"Pistachio::Shader::SetVSBuffer","ph":"X","pid":0,"tid":3648595959,"ts":68137189477},{"cat":"function","dur":0,"name":"Pistachio::RenderCubeMap::BindResource","ph":"X","pid":0,"tid":3648595959,"ts":68137189496},{"cat":"function","dur":0,"name":"Pistachio::VertexBuffer::Bind","ph":"X","pid":0,"tid":3648595959,"ts":68137189513},{"cat":"function","dur":0,"name":"Pistachio::IndexBuffer::Bind","ph":"X","pid":0,"tid":3648595959,"ts":68137189530},{"cat":"function","dur":1,"name":"Pistachio::Shader::Bind","ph":"X","pid":0,"tid":3648595959,"ts":68137189550},{"cat":"function","dur":1,"name":"Pistachio::Shader::Bind","ph":"X","pid":0,"tid":3648595959,"ts":68137189569},{"cat":"function","dur":233,"name":"Pistachio::RenderCubeMap::CreateStack","ph":"X","pid":0,"tid":3648595959,"ts":68137189590},{"cat":"function","dur":29,"name":"Pistachio::ConstantBuffer::Create","ph":"X","pid":0,"tid":3648595959,"ts":68137189914},{"cat":"function","dur":375,"name":"Pistachio::RenderTexture::CreateStack","ph":"X","pid":0,"tid":3648595959,"ts":68137190182},{"cat":"function","dur":164,"name":"Pistachio::RenderTexture::CreateStack","ph":"X","pid":0,"tid":3648595959,"ts":68137190651},{"cat":"function","dur":142,"name":"Pistachio::RenderTexture::CreateStack","ph":"X","pid":0,"tid":3648595959,"ts":68137190857},{"cat":"function","dur":119,"name":"Pistachio::RenderTexture::CreateStack","ph":"X","pid":0,"tid":3648595959,"ts":68137191040},{"cat":"function","dur":126,"name":"Pistachio::RenderTexture::CreateStack","ph":"X","pid":0,"tid":3648595959,"ts":68137191202},{"cat":"function","dur":105,"name":"Pistachio::RenderTexture::CreateStack","ph":"X","pid":0,"tid":3648595959,"ts":68137191368},{"cat":"function","dur":51,"name":"Pistachio::ConstantBuffer::Update","ph":"X","pid":0,"tid":3648595959,"ts":68137191547},{"cat":"function","dur":13,"name":"Pistachio::Shader::SetVSBuffer","ph":"X","pid":0,"tid":3648595959,"ts":68137191653},{"cat":"function","dur":17,"name":"Pistachio::RenderTexture::Bind","ph":"X","pid":0,"tid":3648595959,"ts":68137191704},{"cat":"function","dur":6,"name":"Pistachio::RenderTexture::Clear","ph":"X","pid":0,"tid":3648595959,"ts":68137191760},{"cat":"function","dur":9,"name":"Pistachio::RenderCubeMap::BindResource","ph":"X","pid":0,"tid":3648595959,"ts":68137191813},{"cat":"function","dur":13,"name":"Pistachio::VertexBuffer::Bind","ph":"X","pid":0,"tid":3648595959,"ts":68137191854},{"cat":"function","dur":4,"name":"Pistachio::IndexBuffer::Bind","ph":"X","pid":0,"tid":3648595959,"ts":68137191902},{"cat":"function","dur":24,"name":"Pistachio::RenderTexture::GetRenderTexture","ph":"X","pid":0,"tid":3648595959,"ts":68137192008},{"cat":"function","dur":1,"name":"Pistachio::RenderCubeMap::GetResource","ph":"X","pid":0,"tid":3648595959,"ts":68137192091},{"cat":"function","dur":45,"name":"Pistachio::Texture2D::CopyIntoRegion","ph":"X","pid":0,"tid":3648595959,"ts":68137192123},{"cat":"function","dur":12,"name":"Pistachio::ConstantBuffer::Update","ph":"X","pid":0,"tid":3648595959,"ts":68137192307},{"cat":"function","dur":1,"name":"Pistachio::Shader::SetVSBuffer","ph":"X","pid":0,"tid":3648595959,"ts":68137192348},{"cat":"function","dur":3,"name":"Pistachio::RenderTexture::Bind","ph":"X","pid":0,"tid":3648595959,"ts":68137192365},{"cat":"function","dur":1,"name":"Pistachio::RenderTexture::Clear","ph":"X","pid":0,"tid":3648595959,"ts":68137192383},{"cat":"function","dur":1,"name":"Pistachio::RenderCubeMap::BindResource","ph":"X","pid":0,"tid":3648595959,"ts":68137192399},{"cat":"function","dur":1,"name":"Pistachio::VertexBuffer::Bind","ph":"X","pid":0,"tid":3648595959,"ts":68137192415},{"cat":"function","dur":1,"name":"Pistachio::IndexBuffer::Bind","ph":"X","pid":0,"tid":3648595959,"ts":68137192432},{"cat":"function","dur":1,"name":"Pistachio::RenderTexture::GetRenderTexture","ph":"X","pid":0,"tid":3648595959,"ts":68137192455},{"cat":"function","dur":0,"name":"Pistachio::RenderCubeMap::GetResource","ph":"X","pid":0,"tid":3648595959,"ts":68137192472},{"cat":"function","dur":2,"name":"Pistachio::Texture2D::CopyIntoRegion","ph":"X","pid":0,"tid":3648595959,"ts":68137192488},{"cat":"function","dur":2,"name":"Pistachio::ConstantBuffer::Update","ph":"X","pid":0,"tid":3648595959,"ts":68137192506},{"cat":"function","dur":0,"name":"Pistachio::Shader::SetVSBuffer","ph":"X","pid":0,"tid":3648595959,"ts":68137192524},{"cat":"function","dur":1,"name":"Pistachio::RenderTexture::Bind","ph":"X","pid":0,"tid":3648595959,"ts":68137192540},{"cat":"function","dur":0,"name":"Pistachio::RenderTexture::Clear","ph":"X","pid":0,"tid":3648595959,"ts":68137192557},{"cat":"function","dur":1,"name":"Pistachio::RenderCubeMap::BindResource","ph":"X","pid":0,"tid":3648595959,"ts":68137192572},{"cat":"function","dur":0,"name":"Pistachio::VertexBuffer::Bind","ph":"X","pid":0,"tid":3648595959,"ts":68137192588},{"cat":"function","dur":1,"name":"Pistachio::IndexBuffer::Bind","ph":"X","pid":0,"tid":3648595959,"ts":68137192604},{"cat":"function","dur":0,"name":"Pistachio::RenderTexture::GetRenderTexture","ph":"X","pid":0,"tid":3648595959,"ts":68137192623},{"cat":"function","dur":0,"name":"Pistachio::RenderCubeMap::GetResource","ph":"X","pid":0,"tid":3648595959,"ts":68137192639},{"cat":"function","dur":1,"name":"Pistachio::Texture2D::CopyIntoRegion","ph":"X","pid":0,"tid":3648595959,"ts":68137192655},{"cat":"function","dur":2,"name":"Pistachio::ConstantBuffer::Update","ph":"X","pid":0,"tid":3648595959,"ts":68137192672},{"cat":"function","dur":1,"name":"Pistachio::Shader::SetVSBuffer","ph":"X","pid":0,"tid":3648595959,"ts":68137192689},{"cat":"function","dur":1,"name":"Pistachio::RenderTexture::Bind","ph":"X","pid":0,"tid":3648595959,"ts":68137192705},{"cat":"function","dur":0,"name":"Pistachio::RenderTexture::Clear","ph":"X","pid":0,"tid":3648595959,"ts":68137192722},{"cat":"function","dur":1,"name":"Pistachio::RenderCubeMap::BindResource","ph":"X","pid":0,"tid":3648595959,"ts":68137192737},{"cat":"function","dur":1,"name":"Pistachio::VertexBuffer::Bind","ph":"X","pid":0,"tid":3648595959,"ts":68137192753},{"cat":"function","dur":0,"name":"Pistachio::IndexBuffer::Bind","ph":"X","pid":0,"tid":3648595959,"ts":68137192769},{"cat":"function","dur":1,"name":"Pistachio::RenderTexture::GetRenderTexture","ph":"X","pid":0,"tid":3648595959,"ts":68137192786},{"cat":"function","dur":0,"name":"Pistachio::RenderCubeMap::GetResource","ph":"X","pid":0,"tid":3648595959,"ts":68137192804},{"cat":"function","dur":2,"name":"Pistachio::Texture2D::CopyIntoRegion","ph":"X","pid":0,"tid":3648595959,"ts":68137192820},{"cat":"function","dur":1,"name":"Pistachio::ConstantBuffer::Update","ph":"X","pid":0,"tid":3648595959,"ts":68137192838},{"cat":"function","dur":0,"name":"Pistachio::Shader::SetVSBuffer","ph":"X","pid":0,"tid":3648595959,"ts":68137192858},{"cat":"function","dur":2,"name":"Pistachio::RenderTexture::Bind","ph":"X","pid":0,"tid":3648595959,"ts":68137192880},{"cat":"function","dur":0,"name":"Pistachio::RenderTexture::Clear","ph":"X","pid":0,"tid":3648595959,"ts":68137192902},{"cat":"function","dur":1,"name":"Pistachio::RenderCubeMap::BindResource","ph":"X","pid":0,"tid":3648595959,"ts":68137192920},{"cat":"function","dur":1,"name":"Pistachio::VertexBuffer::Bind","ph":"X","pid":0,"tid":3648595959,"ts":68137192937},{"cat":"function","dur":0,"name":"Pistachio::IndexBuffer::Bind","ph":"X","pid":0,"tid":3648595959,"ts":68137192953},{"cat":"function","dur":0,"name":"Pistachio::RenderTexture::GetRenderTexture","ph":"X","pid":0,"tid":3648595959,"ts":68137192972},{"cat":"function","dur":0,"name":"Pistachio::RenderCubeMap::GetResource","ph":"X","pid":0,"tid":3648595959,"ts":68137192988},{"cat":"function","dur":1,"name":"Pistachio::Texture2D::CopyIntoRegion","ph":"X","pid":0,"tid":3648595959,"ts":68137193003},{"cat":"function","dur":6,"name":"Pistachio::ConstantBuffer::Update","ph":"X","pid":0,"tid":3648595959,"ts":68137193020},{"cat":"function","dur":1,"name":"Pistachio::Shader::SetVSBuffer","ph":"X","pid":0,"tid":3648595959,"ts":68137193042},{"cat":"function","dur":2,"name":"Pistachio::RenderTexture::Bind","ph":"X","pid":0,"tid":3648595959,"ts":68137193058},{"cat":"function","dur":1,"name":"Pistachio::RenderTexture::Clear","ph":"X","pid":0,"tid":3648595959,"ts":68137193075},{"cat":"function","dur":0,"name":"Pistachio::RenderCubeMap::BindResource","ph":"X","pid":0,"tid":3648595959,"ts":68137193092},{"cat":"function","dur":0,"name":"Pistachio::VertexBuffer::Bind","ph":"X","pid":0,"tid":3648595959,"ts":68137193108},{"cat":"function","dur":0,"name":"Pistachio::IndexBuffer::Bind","ph":"X","pid":0,"tid":3648595959,"ts":68137193124},{"cat":"function","dur":0,"name":"Pistachio::RenderTexture::GetRenderTexture","ph":"X","pid":0,"tid":3648595959,"ts":68137193143},{"cat":"function","dur":0,"name":"Pistachio::RenderCubeMap::GetResource","ph":"X","pid":0,"tid":3648595959,"ts":68137193159},{"cat":"function","dur":2,"name":"Pistachio::Texture2D::CopyIntoRegion","ph":"X","pid":0,"tid":3648595959,"ts":68137193175},{"cat":"function","dur":206,"name":"Pistachio::RenderTexture::CreateStack","ph":"X","pid":0,"tid":3648595959,"ts":68137193195},{"cat":"function","dur":125,"name":"Pistachio::RenderTexture::CreateStack","ph":"X","pid":0,"tid":3648595959,"ts":68137193447},{"cat":"function","dur":109,"name":"Pistachio::RenderTexture::CreateStack","ph":"X","pid":0,"tid":3648595959,"ts":68137193607},{"cat":"function","dur":120,"name":"Pistachio::RenderTexture::CreateStack","ph":"X","pid":0,"tid":3648595959,"ts":68137193756},{"cat":"function","dur":95,"name":"Pistachio::RenderTexture::CreateStack","ph":"X","pid":0,"tid":3648595959,"ts":68137193913},{"cat":"function","dur":98,"name":"Pistachio::RenderTexture::CreateStack","ph":"X","pid":0,"tid":3648595959,"ts":68137194046},{"cat":"function","dur":5,"name":"Pistachio::ConstantBuffer::Update","ph":"X","pid":0,"tid":3648595959,"ts":68137194187},{"cat":"function","dur":1,"name":"Pistachio::Shader::SetVSBuffer","ph":"X","pid":0,"tid":3648595959,"ts":68137194212},{"cat":"function","dur":2,"name":"Pistachio::RenderTexture::Bind","ph":"X","pid":0,"tid":3648595959,"ts":68137194229},{"cat":"function","dur":1,"name":"Pistachio::RenderTexture::Clear","ph":"X","pid":0,"tid":3648595959,"ts":68137194247},{"cat":"function","dur":0,"name":"Pistachio::RenderCubeMap::BindResource","ph":"X","pid":0,"tid":3648595959,"ts":68137194264},{"cat":"function","dur":1,"name":"Pistachio::VertexBuffer::Bind","ph":"X","pid":0,"tid":3648595959,"ts":68137194281},{"cat":"function","dur":1,"name":"Pistachio::IndexBuffer::Bind","ph":"X","pid":0,"tid":3648595959,"ts":68137194297},{"cat":"function","dur":1,"name":"Pistachio::RenderTexture::GetRenderTexture","ph":"X","pid":0,"tid":3648595959,"ts":68137194319},{"cat":"function","dur":0,"name":"Pistachio::RenderCubeMap::GetResource","ph":"X","pid":0,"tid":3648595959,"ts":68137194336},{"cat":"function","dur":3,"name":"Pistachio::Texture2D::CopyIntoRegion","ph":"X","pid":0,"tid":3648595959,"ts":68137194352},{"cat":"function","dur":3,"name":"Pistachio::ConstantBuffer::Update","ph":"X","pid":0,"tid":3648595959,"ts":68137194371},{"cat":"function","dur":0,"name":"Pistachio::Shader::SetVSBuffer","ph":"X","pid":0,"tid":3648595959,"ts":68137194390},{"cat":"function","dur":1,"name":"Pistachio::RenderTexture::Bind","ph":"X","pid":0,"tid":3648595959,"ts":68137194408},{"cat":"function","dur":1,"name":"Pistachio::RenderTexture::Clear","ph":"X","pid":0,"tid":3648595959,"ts":68137194433},{"cat":"function","dur":0,"name":"Pistachio::RenderCubeMap::BindResource","ph":"X","pid":0,"tid":3648595959,"ts":68137194456},{"cat":"function","dur":1,"name":"Pistachio::VertexBuffer::Bind","ph":"X","pid":0,"tid":3648595959,"ts":68137194478},{"cat":"function","dur":1,"name":"Pistachio::IndexBuffer::Bind","ph":"X","pid":0,"tid":3648595959,"ts":68137194501},{"cat":"function","dur":1,"name":"Pistachio::RenderTexture::GetRenderTexture","ph":"X","pid":0,"tid":3648595959,"ts":68137194528},{"cat":"function","dur":1,"name":"Pistachio::RenderCubeMap::GetResource","ph":"X","pid":0,"tid":3648595959,"ts":68137194546},{"cat":"function","dur":2,"name":"Pistachio::Texture2D::CopyIntoRegion","ph":"X","pid":0,"tid":3648595959,"ts":68137194561},{"cat":"function","dur":3,"name":"Pistachio::ConstantBuffer::Update","ph":"X","pid":0,"tid":3648595959,"ts":68137194579},{"cat":"function","dur":1,"name":"Pistachio::Shader::SetVSBuffer","ph":"X","pid":0,"tid":3648595959,"ts":68137194598},{"cat":"function","dur":3,"name":"Pistachio::RenderTexture::Bind","ph":"X","pid":0,"tid":3648595959,"ts":68137194615},{"cat":"function","dur":0,"name":"Pistachio::RenderTexture::Clear","ph":"X","pid":0,"tid":3648595959,"ts":68137194643},{"cat":"function","dur":1,"name":"Pistachio::RenderCubeMap::BindResource","ph":"X","pid":0,"tid":3648595959,"ts":68137194668},{"cat":"function","dur":1,"name":"Pistachio::VertexBuffer::Bind","ph":"X","pid":0,"tid":3648595959,"ts":68137194686},{"cat":"function","dur":0,"name":"Pistachio::IndexBuffer::Bind","ph":"X","pid":0,"tid":3648595959,"ts":68137194702},{"cat":"function","dur":1,"name":"Pistachio::RenderTexture::GetRenderTexture","ph":"X","pid":0,"tid":3648595959,"ts":68137194720},{"cat":"function","dur":0,"name":"Pistachio::RenderCubeMap::GetResource","ph":"X","pid":0,"tid":3648595959,"ts":68137194736},{"cat":"function","dur":1,"name":"Pistachio::Texture2D::CopyIntoRegion","ph":"X","pid":0,"tid":3648595959,"ts":68137194752},{"cat":"function","dur":3,"name":"Pistachio::ConstantBuffer::Update","ph":"X","pid":0,"tid":3648595959,"ts":68137194769},{"cat":"function","dur":1,"name":"Pistachio::Shader::SetVSBuffer","ph":"X","pid":0,"tid":3648595959,"ts":68137194788},{"cat":"function","dur":2,"name":"Pistachio::RenderTexture::Bind","ph":"X","pid":0,"tid":3648595959,"ts":68137194804},{"cat":"function","dur":1,"name":"Pistachio::RenderTexture::Clear","ph":"X","pid":0,"tid":3648595959,"ts":68137194821},{"cat":"function","dur":0,"name":"Pistachio::RenderCubeMap::BindResource","ph":"X","pid":0,"tid":3648595959,"ts":68137194837},{"cat":"function","dur":0,"name":"Pistachio::VertexBuffer::Bind","ph":"X","pid":0,"tid":3648595959,"ts":68137194853},{"cat":"function","dur":1,"name":"Pistachio::IndexBuffer::Bind","ph":"X","pid":0,"tid":3648595959,"ts":68137194868},{"cat":"function","dur":0,"name":"Pistachio::RenderTexture::GetRenderTexture","ph":"X","pid":0,"tid":3648595959,"ts":68137194886},{"cat":"function","dur":0,"name":"Pistachio::RenderCubeMap::GetResource","ph":"X","pid":0,"tid":3648595959,"ts":68137194902},{"cat":"function","dur":4,"name":"Pistachio::Texture2D::CopyIntoRegion","ph":"X","pid":0,"tid":3648595959,"ts":68137194917},{"cat":"function","dur":2,"name":"Pistachio::ConstantBuffer::Update","ph":"X","pid":0,"tid":3648595959,"ts":68137194938},{"cat":"function","dur":1,"name":"Pistachio::Shader::SetVSBuffer","ph":"X","pid":0,"tid":3648595959,"ts":68137194955},{"cat":"function","dur":2,"name":"Pistachio::RenderTexture::Bind","ph":"X","pid":0,"tid":3648595959,"ts":68137194971},{"cat":"function","dur":0,"name":"Pistachio::RenderTexture::Clear","ph":"X","pid":0,"tid":3648595959,"ts":68137194988},{"cat":"function","dur":1,"name":"Pistachio::RenderCubeMap::BindResource","ph":"X","pid":0,"tid":3648595959,"ts":68137195003},{"cat":"function","dur":1,"name":"Pistachio::VertexBuffer::Bind","ph":"X","pid":0,"tid":3648595959,"ts":68137195020},{"cat":"function","dur":0,"name":"Pistachio::IndexBuffer::Bind","ph":"X","pid":0,"tid":3648595959,"ts":68137195037},{"cat":"function","dur":0,"name":"Pistachio::RenderTexture::GetRenderTexture","ph":"X","pid":0,"tid":3648595959,"ts":68137195055},{"cat":"function","dur":0,"name":"Pistachio::RenderCubeMap::GetResource","ph":"X","pid":0,"tid":3648595959,"ts":68137195071},{"cat":"function","dur":2,"name":"Pistachio::Texture2D::CopyIntoRegion","ph":"X","pid":0,"tid":3648595959,"ts":68137195086},{"cat":"function","dur":2,"name":"Pistachio::ConstantBuffer::Update","ph":"X","pid":0,"tid":3648595959,"ts":68137195105},{"cat":"function","dur":1,"name":"Pistachio::Shader::SetVSBuffer","ph":"X","pid":0,"tid":3648595959,"ts":68137195123},{"cat":"function","dur":1,"name":"Pistachio::RenderTexture::Bind","ph":"X","pid":0,"tid":3648595959,"ts":68137195139},{"cat":"function","dur":0,"name":"Pistachio::RenderTexture::Clear","ph":"X","pid":0,"tid":3648595959,"ts":68137195156},{"cat":"function","dur":1,"name":"Pistachio::RenderCubeMap::BindResource","ph":"X","pid":0,"tid":3648595959,"ts":68137195171},{"cat":"function","dur":0,"name":"Pistachio::VertexBuffer::Bind","ph":"X","pid":0,"tid":3648595959,"ts":68137195191},{"cat":"function","dur":1,"name":"Pistachio::IndexBuffer::Bind","ph":"X","pid":0,"tid":3648595959,"ts":68137195214},{"cat":"function","dur":0,"name":"Pistachio::RenderTexture::GetRenderTexture","ph":"X","pid":0,"tid":3648595959,"ts":68137195241},{"cat":"function","dur":0,"name":"Pistachio::RenderCubeMap::GetResource","ph":"X","pid":0,"tid":3648595959,"ts":68137195266},{"cat":"function","dur":2,"name":"Pistachio::Texture2D::CopyIntoRegion","ph":"X","pid":0,"tid":3648595959,"ts":68137195282},{"cat":"function","dur":223,"name":"Pistachio::RenderTexture::CreateStack","ph":"X","pid":0,"tid":3648595959,"ts":68137195308},{"cat":"function","dur":106,"name":"Pistachio::RenderTexture::CreateStack","ph":"X","pid":0,"tid":3648595959,"ts":68137195579},{"cat":"function","dur":102,"name":"Pistachio::RenderTexture::CreateStack","ph":"X","pid":0,"tid":3648595959,"ts":68137195720},{"cat":"function","dur":99,"name":"Pistachio::RenderTexture::CreateStack","ph":"X","pid":0,"tid":3648595959,"ts":68137195855},{"cat":"function","dur":94,"name":"Pistachio::RenderTexture::CreateStack","ph":"X","pid":0,"tid":3648595959,"ts":68137195992},{"cat":"function","dur":101,"name":"Pistachio::RenderTexture::CreateStack","ph":"X","pid":0,"tid":3648595959,"ts":68137196122},{"cat":"function","dur":15,"name":"Pistachio::ConstantBuffer::Update","ph":"X","pid":0,"tid":3648595959,"ts":68137196263},{"cat":"function","dur":1,"name":"Pistachio::Shader::SetVSBuffer","ph":"X","pid":0,"tid":3648595959,"ts":68137196300},{"cat":"function","dur":3,"name":"Pistachio::RenderTexture::Bind","ph":"X","pid":0,"tid":3648595959,"ts":68137196317},{"cat":"function","dur":0,"name":"Pistachio::RenderTexture::Clear","ph":"X","pid":0,"tid":3648595959,"ts":68137196337},{"cat":"function","dur":1,"name":"Pistachio::RenderCubeMap::BindResource","ph":"X","pid":0,"tid":3648595959,"ts":68137196353},{"cat":"function","dur":1,"name":"Pistachio::VertexBuffer::Bind","ph":"X","pid":0,"tid":3648595959,"ts":68137196370},{"cat":"function","dur":1,"name":"Pistachio::IndexBuffer::Bind","ph":"X","pid":0,"tid":3648595959,"ts":68137196386},{"cat":"function","dur":0,"name":"Pistachio::RenderTexture::GetRenderTexture","ph":"X","pid":0,"tid":3648595959,"ts":68137196409},{"cat":"function","dur":0,"name":"Pistachio::RenderCubeMap::GetResource","ph":"X","pid":0,"tid":3648595959,"ts":68137196426},{"cat":"function","dur":3,"name":"Pistachio::Texture2D::CopyIntoRegion","ph":"X","pid":0,"tid":3648595959,"ts":68137196441},{"cat":"function","dur":2,"name":"Pistachio::ConstantBuffer::Update","ph":"X","pid":0,"tid":3648595959,"ts":68137196460},{"cat":"function","dur":0,"name":"Pistachio::Shader::SetVSBuffer","ph":"X","pid":0,"tid":3648595959,"ts":68137196478},{"cat":"function","dur":1,"name":"Pistachio::RenderTexture::Bind","ph":"X","pid":0,"tid":3648595959,"ts":68137196494},{"cat":"function","dur":0,"name":"Pistachio::RenderTexture::Clear","ph":"X","pid":0,"tid":3648595959,"ts":68137196546},{"cat":"function","dur":1,"name":"Pistachio::RenderCubeMap::BindResource","ph":"X","pid":0,"tid":3648595959,"ts":68137196565},{"cat":"function","dur":1,"name":"Pistachio::VertexBuffer::Bind","ph":"X","pid":0,"tid":3648595959,"ts":68137196581},{"cat":"function","dur":0,"name":"Pistachio::IndexBuffer::Bind","ph":"X","pid":0,"tid":3648595959,"ts":68137196598},{"cat":"function","dur":1,"name":"Pistachio::RenderTexture::GetRenderTexture","ph":"X","pid":0,"tid":3648595959,"ts":68137196616},{"cat":"function","dur":1,"name":"Pistachio::RenderCubeMap::GetResource","ph":"X","pid":0,"tid":3648595959,"ts":68137196632},{"cat":"function","dur":2,"name":"Pistachio::Texture2D::CopyIntoRegion","ph":"X","pid":0,"tid":3648595959,"ts":68137196648},{"cat":"function","dur":2,"name":"Pistachio::ConstantBuffer::Update","ph":"X","pid":0,"tid":3648595959,"ts":68137196665},{"cat":"function","dur":0,"name":"Pistachio::Shader::SetVSBuffer","ph":"X","pid":0,"tid":3648595959,"ts":68137196683},{"cat":"function","dur":1,"name":"Pistachio::RenderTexture::Bind","ph":"X","pid":0,"tid":3648595959,"ts":68137196699},{"cat":"function","dur":0,"name":"Pistachio::RenderTexture::Clear","ph":"X","pid":0,"tid":3648595959,"ts":68137196715},{"cat":"function","dur":1,"name":"Pistachio::RenderCubeMap::BindResource","ph":"X","pid":0,"tid":3648595959,"ts":68137196730},{"cat":"function","dur":1,"name":"Pistachio::VertexBuffer::Bind","ph":"X","pid":0,"tid":3648595959,"ts":68137196746},{"cat":"function","dur":0,"name":"Pistachio::IndexBuffer::Bind","ph":"X","pid":0,"tid":3648595959,"ts":68137196762},{"cat":"function","dur":0,"name":"Pistachio::RenderTexture::GetRenderTexture","ph":"X","pid":0,"tid":3648595959,"ts":68137196780},{"cat":"function","dur":0,"name":"Pistachio::RenderCubeMap::GetResource","ph":"X","pid":0,"tid":3648595959,"ts":68137196796},{"cat":"function","dur":2,"name":"Pistachio::Texture2D::CopyIntoRegion","ph":"X","pid":0,"tid":3648595959,"ts":68137196811},{"cat":"function","dur":2,"name":"Pistachio::ConstantBuffer::Update","ph":"X","pid":0,"tid":3648595959,"ts":68137196828},{"cat":"function","dur":0,"name":"Pistachio::Shader::SetVSBuffer","ph":"X","pid":0,"tid":3648595959,"ts":68137196845},{"cat":"function","dur":2,"name":"Pistachio::RenderTexture::Bind","ph":"X","pid":0,"tid":3648595959,"ts":68137196860},{"cat":"function","dur":1,"name":"Pistachio::RenderTexture::Clear","ph":"X","pid":0,"tid":3648595959,"ts":68137196876},{"cat":"function","dur":1,"name":"Pistachio::RenderCubeMap::BindResource","ph":"X","pid":0,"tid":3648595959,"ts":68137196892},{"cat":"function","dur":1,"name":"Pistachio::VertexBuffer::Bind","ph":"X","pid":0,"tid":3648595959,"ts":68137196908},{"cat":"function","dur":1,"name":"Pistachio::IndexBuffer::Bind","ph":"X","pid":0,"tid":3648595959,"ts":68137196923},{"cat":"function","dur":0,"name":"Pistachio::RenderTexture::GetRenderTexture","ph":"X","pid":0,"tid":3648595959,"ts":68137196941},{"cat":"function","dur":0,"name":"Pistachio::RenderCubeMap::GetResource","ph":"X","pid":0,"tid":3648595959,"ts":68137196957},{"cat":"function","dur":1,"name":"Pistachio::Texture2D::CopyIntoRegion","ph":"X","pid":0,"tid":3648595959,"ts":68137196972},{"cat":"function","dur":2,"name":"Pistachio::ConstantBuffer::Update","ph":"X","pid":0,"tid":3648595959,"ts":68137196989},{"cat":"function","dur":1,"name":"Pistachio::Shader::SetVSBuffer","ph":"X","pid":0,"tid":3648595959,"ts":68137197006},{"cat":"function","dur":1,"name":"Pistachio::RenderTexture::Bind","ph":"X","pid":0,"tid":3648595959,"ts":68137197022},{"cat":"function","dur":0,"name":"Pistachio::RenderTexture::Clear","ph":"X","pid":0,"tid":3648595959,"ts":68137197039},{"cat":"function","dur":1,"name":"Pistachio::RenderCubeMap::BindResource","ph":"X","pid":0,"tid":3648595959,"ts":68137197054},{"cat":"function","dur":0,"name":"Pistachio::VertexBuffer::Bind","ph":"X","pid":0,"tid":3648595959,"ts":68137197070},{"cat":"function","dur":1,"name":"Pistachio::IndexBuffer::Bind","ph":"X","pid":0,"tid":3648595959,"ts":68137197085},{"cat":"function","dur":1,"name":"Pistachio::RenderTexture::GetRenderTexture","ph":"X","pid":0,"tid":3648595959,"ts":68137197103},{"cat":"function","dur":0,"name":"Pistachio::RenderCubeMap::GetResource","ph":"X","pid":0,"tid":3648595959,"ts":68137197120},{"cat":"function","dur":1,"name":"Pistachio::Texture2D::CopyIntoRegion","ph":"X","pid":0,"tid":3648595959,"ts":68137197135},{"cat":"function","dur":3,"name":"Pistachio::ConstantBuffer::Update","ph":"X","pid":0,"tid":3648595959,"ts":68137197152},{"cat":"function","dur":1,"name":"Pistachio::Shader::SetVSBuffer","ph":"X","pid":0,"tid":3648595959,"ts":68137197171},{"cat":"function","dur":1,"name":"Pistachio::RenderTexture::Bind","ph":"X","pid":0,"tid":3648595959,"ts":68137197187},{"cat":"function","dur":1,"name":"Pistachio::RenderTexture::Clear","ph":"X","pid":0,"tid":3648595959,"ts":68137197203},{"cat":"function","dur":1,"name":"Pistachio::RenderCubeMap::BindResource","ph":"X","pid":0,"tid":3648595959,"ts":68137197218},{"cat":"function","dur":1,"name":"Pistachio::VertexBuffer::Bind","ph":"X","pid":0,"tid":3648595959,"ts":68137197234},{"cat":"function","dur":1,"name":"Pistachio::IndexBuffer::Bind","ph":"X","pid":0,"tid":3648595959,"ts":68137197249},{"cat":"function","dur":1,"name":"Pistachio::RenderTexture::GetRenderTexture","ph":"X","pid":0,"tid":3648595959,"ts":68137197267},{"cat":"function","dur":0,"name":"Pistachio::RenderCubeMap::GetResource","ph":"X","pid":0,"tid":3648595959,"ts":68137197283},{"cat":"function","dur":1,"name":"Pistachio::Texture2D::CopyIntoRegion","ph":"X","pid":0,"tid":3648595959,"ts":68137197298},{"cat":"function","dur":103,"name":"Pistachio::RenderTexture::CreateStack","ph":"X","pid":0,"tid":3648595959,"ts":68137197315},{"cat":"function","dur":106,"name":"Pistachio::RenderTexture::CreateStack","ph":"X","pid":0,"tid":3648595959,"ts":68137197444},{"cat":"function","dur":91,"name":"Pistachio::RenderTexture::CreateStack","ph":"X","pid":0,"tid":3648595959,"ts":68137197587},{"cat":"function","dur":132,"name":"Pistachio::RenderTexture::CreateStack","ph":"X","pid":0,"tid":3648595959,"ts":68137197713},{"cat":"function","dur":90,"name":"Pistachio::RenderTexture::CreateStack","ph":"X","pid":0,"tid":3648595959,"ts":68137197881},{"cat":"function","dur":91,"name":"Pistachio::RenderTexture::CreateStack","ph":"X","pid":0,"tid":3648595959,"ts":68137198004},{"cat":"function","dur":4,"name":"Pistachio::ConstantBuffer::Update","ph":"X","pid":0,"tid":3648595959,"ts":68137198131},{"cat":"function","dur":1,"name":"Pistachio::Shader::SetVSBuffer","ph":"X","pid":0,"tid":3648595959,"ts":68137198155},{"cat":"function","dur":1,"name":"Pistachio::RenderTexture::Bind","ph":"X","pid":0,"tid":3648595959,"ts":68137198172},{"cat":"function","dur":1,"name":"Pistachio::RenderTexture::Clear","ph":"X","pid":0,"tid":3648595959,"ts":68137198188},{"cat":"function","dur":0,"name":"Pistachio::RenderCubeMap::BindResource","ph":"X","pid":0,"tid":3648595959,"ts":68137198205},{"cat":"function","dur":0,"name":"Pistachio::VertexBuffer::Bind","ph":"X","pid":0,"tid":3648595959,"ts":68137198221},{"cat":"function","dur":0,"name":"Pistachio::IndexBuffer::Bind","ph":"X","pid":0,"tid":3648595959,"ts":68137198237},{"cat":"function","dur":0,"name":"Pistachio::RenderTexture::GetRenderTexture","ph":"X","pid":0,"tid":3648595959,"ts":68137198257},{"cat":"function","dur":0,"name":"Pistachio::RenderCubeMap::GetResource","ph":"X","pid":0,"tid":3648595959,"ts":68137198273},{"cat":"function","dur":2,"name":"Pistachio::Texture2D::CopyIntoRegion","ph":"X","pid":0,"tid":3648595959,"ts":68137198288},{"cat":"function","dur":2,"name":"Pistachio::ConstantBuffer::Update","ph":"X","pid":0,"tid":3648595959,"ts":68137198306},{"cat":"function","dur":1,"name":"Pistachio::Shader::SetVSBuffer","ph":"X","pid":0,"tid":3648595959,"ts":68137198323},{"cat":"function","dur":1,"name":"Pistachio::RenderTexture::Bind","ph":"X","pid":0,"tid":3648595959,"ts":68137198339},{"cat":"function","dur":0,"name":"Pistachio::RenderTexture::Clear","ph":"X","pid":0,"tid":3648595959,"ts":68137198356},{"cat":"function","dur":0,"name":"Pistachio::RenderCubeMap::BindResource","ph":"X","pid":0,"tid":3648595959,"ts":68137198373},{"cat":"function","dur":1,"name":"Pistachio::VertexBuffer::Bind","ph":"X","pid":0,"tid":3648595959,"ts":68137198389},{"cat":"function","dur":0,"name":"Pistachio::IndexBuffer::Bind","ph":"X","pid":0,"tid":3648595959,"ts":68137198405},{"cat":"function","dur":0,"name":"Pistachio::RenderTexture::GetRenderTexture","ph":"X","pid":0,"tid":3648595959,"ts":68137198423},{"cat":"function","dur":0,"name":"Pistachio::RenderCubeMap::GetResource","ph":"X","pid":0,"tid":3648595959,"ts":68137198439},{"cat":"function","dur":2,"name":"Pistachio::Texture2D::CopyIntoRegion","ph":"X","pid":0,"tid":3648595959,"ts":68137198454},{"cat":"function","dur":2,"name":"Pistachio::ConstantBuffer::Update","ph":"X","pid":0,"tid":3648595959,"ts":68137198471},{"cat":"function","dur":1,"name":"Pistachio::Shader::SetVSBuffer","ph":"X","pid":0,"tid":3648595959,"ts":68137198489},{"cat":"function","dur":1,"name":"Pistachio::RenderTexture::Bind","ph":"X","pid":0,"tid":3648595959,"ts":68137198505},{"cat":"function","dur":0,"name":"Pistachio::RenderTexture::Clear","ph":"X","pid":0,"tid":3648595959,"ts":68137198522},{"cat":"function","dur":1,"name":"Pistachio::RenderCubeMap::BindResource","ph":"X","pid":0,"tid":3648595959,"ts":68137198537},{"cat":"function","dur":1,"name":"Pistachio::VertexBuffer::Bind","ph":"X","pid":0,"tid":3648595959,"ts":68137198553},{"cat":"function","dur":1,"name":"Pistachio::IndexBuffer::Bind","ph":"X","pid":0,"tid":3648595959,"ts":68137198569},{"cat":"function","dur":1,"name":"Pistachio::RenderTexture::GetRenderTexture","ph":"X","pid":0,"tid":3648595959,"ts":68137198587},{"cat":"function","dur":1,"name":"Pistachio::RenderCubeMap::GetResource","ph":"X","pid":0,"tid":3648595959,"ts":68137198603},{"cat":"function","dur":1,"name":"Pistachio::Texture2D::CopyIntoRegion","ph":"X","pid":0,"tid":3648595959,"ts":68137198619},{"cat":"function","dur":1,"name":"Pistachio::ConstantBuffer::Update","ph":"X","pid":0,"tid":3648595959,"ts":68137198636},{"cat":"function","dur":0,"name":"Pistachio::Shader::SetVSBuffer","ph":"X","pid":0,"tid":3648595959,"ts":68137198653},{"cat":"function","dur":2,"name":"Pistachio::RenderTexture::Bind","ph":"X","pid":0,"tid":3648595959,"ts":68137198669},{"cat":"function","dur":1,"name":"Pistachio::RenderTexture::Clear","ph":"X","pid":0,"tid":3648595959,"ts":68137198686},{"cat":"function","dur":0,"name":"Pistachio::RenderCubeMap::BindResource","ph":"X","pid":0,"tid":3648595959,"ts":68137198702},{"cat":"function","dur":1,"name":"Pistachio::VertexBuffer::Bind","ph":"X","pid":0,"tid":3648595959,"ts":68137198717},{"cat":"function","dur":1,"name":"Pistachio::IndexBuffer::Bind","ph":"X","pid":0,"tid":3648595959,"ts":68137198733},{"cat":"function","dur":1,"name":"Pistachio::RenderTexture::GetRenderTexture","ph":"X","pid":0,"tid":3648595959,"ts":68137198751},{"cat":"function","dur":0,"name":"Pistachio::RenderCubeMap::GetResource","ph":"X","pid":0,"tid":3648595959,"ts":68137198768},{"cat":"function","dur":1,"name":"Pistachio::Texture2D::CopyIntoRegion","ph":"X","pid":0,"tid":3648595959,"ts":68137198783},{"cat":"function","dur":2,"name":"Pistachio::ConstantBuffer::Update","ph":"X","pid":0,"tid":3648595959,"ts":68137198799},{"cat":"function","dur":0,"name":"Pistachio::Shader::SetVSBuffer","ph":"X","pid":0,"tid":3648595959,"ts":68137198817},{"cat":"function","dur":1,"name":"Pistachio::RenderTexture::Bind","ph":"X","pid":0,"tid":3648595959,"ts":68137198832},{"cat":"function","dur":1,"name":"Pistachio::RenderTexture::Clear","ph":"X","pid":0,"tid":3648595959,"ts":68137198848},{"cat":"function","dur":1,"name":"Pistachio::RenderCubeMap::BindResource","ph":"X","pid":0,"tid":3648595959,"ts":68137198863},{"cat":"function","dur":1,"name":"Pistachio::VertexBuffer::Bind","ph":"X","pid":0,"tid":3648595959,"ts":68137198879},{"cat":"function","dur":0,"name":"Pistachio::IndexBuffer::Bind","ph":"X","pid":0,"tid":3648595959,"ts":68137198896},{"cat":"function","dur":0,"name":"Pistachio::RenderTexture::GetRenderTexture","ph":"X","pid":0,"tid":3648595959,"ts":68137198914},{"cat":"function","dur":0,"name":"Pistachio::RenderCubeMap::GetResource","ph":"X","pid":0,"tid":3648595959,"ts":68137198931},{"cat":"function","dur":1,"name":"Pistachio::Texture2D::CopyIntoRegion","ph":"X","pid":0,"tid":3648595959,"ts":68137198947},{"cat":"function","dur":2,"name":"Pistachio::ConstantBuffer::Update","ph":"X","pid":0,"tid":3648595959,"ts":68137198964},{"cat":"function","dur":1,"name":"Pistachio::Shader::SetVSBuffer","ph":"X","pid":0,"tid":3648595959,"ts":68137198981},{"cat":"function","dur":1,"name":"Pistachio::RenderTexture::Bind","ph":"X","pid":0,"tid":3648595959,"ts":68137198997},{"cat":"function","dur":0,"name":"Pistachio::RenderTexture::Clear","ph":"X","pid":0,"tid":3648595959,"ts":68137199014},{"cat":"function","dur":0,"name":"Pistachio::RenderCubeMap::BindResource","ph":"X","pid":0,"tid":3648595959,"ts":68137199030},{"cat":"function","dur":0,"name":"Pistachio::VertexBuffer::Bind","ph":"X","pid":0,"tid":3648595959,"ts":68137199045},{"cat":"function","dur":1,"name":"Pistachio::IndexBuffer::Bind","ph":"X","pid":0,"tid":3648595959,"ts":68137199060},{"cat":"function","dur":0,"name":"Pistachio::RenderTexture::GetRenderTexture","ph":"X","pid":0,"tid":3648595959,"ts":68137199078},{"cat":"function","dur":0,"name":"Pistachio::RenderCubeMap::GetResource","ph":"X","pid":0,"tid":3648595959,"ts":68137199094},{"cat":"function","dur":1,"name":"Pistachio::Texture2D::CopyIntoRegion","ph":"X","pid":0,"tid":3648595959,"ts":68137199109},{"cat":"function","dur":102,"name":"Pistachio::RenderTexture::CreateStack","ph":"X","pid":0,"tid":3648595959,"ts":68137199126},{"cat":"function","dur":122,"name":"Pistachio::RenderTexture::CreateStack","ph":"X","pid":0,"tid":3648595959,"ts":68137199253},{"cat":"function","dur":101,"name":"Pistachio::RenderTexture::CreateStack","ph":"X","pid":0,"tid":3648595959,"ts":68137199411},{"cat":"function","dur":89,"name":"Pistachio::RenderTexture::CreateStack","ph":"X","pid":0,"tid":3648595959,"ts":68137199549},{"cat":"function","dur":99,"name":"Pistachio::RenderTexture::CreateStack","ph":"X","pid":0,"tid":3648595959,"ts":68137199673},{"cat":"function","dur":89,"name":"Pistachio::RenderTexture::CreateStack","ph":"X","pid":0,"tid":3648595959,"ts":68137199807},{"cat":"function","dur":3,"name":"Pistachio::ConstantBuffer::Update","ph":"X","pid":0,"tid":3648595959,"ts":68137199931},{"cat":"function","dur":1,"name":"Pistachio::Shader::SetVSBuffer","ph":"X","pid":0,"tid":3648595959,"ts":68137199954},{"cat":"function","dur":2,"name":"Pistachio::RenderTexture::Bind","ph":"X","pid":0,"tid":3648595959,"ts":68137199971},{"cat":"function","dur":0,"name":"Pistachio::RenderTexture::Clear","ph":"X","pid":0,"tid":3648595959,"ts":68137199989},{"cat":"function","dur":0,"name":"Pistachio::RenderCubeMap::BindResource","ph":"X","pid":0,"tid":3648595959,"ts":68137200005},{"cat":"function","dur":1,"name":"Pistachio::VertexBuffer::Bind","ph":"X","pid":0,"tid":3648595959,"ts":68137200021},{"cat":"function","dur":0,"name":"Pistachio::IndexBuffer::Bind","ph":"X","pid":0,"tid":3648595959,"ts":68137200037},{"cat":"function","dur":1,"name":"Pistachio::RenderTexture::GetRenderTexture","ph":"X","pid":0,"tid":3648595959,"ts":68137200056},{"cat":"function","dur":0,"name":"Pistachio::RenderCubeMap::GetResource","ph":"X","pid":0,"tid":3648595959,"ts":68137200073},{"cat":"function","dur":2,"name":"Pistachio::Texture2D::CopyIntoRegion","ph":"X","pid":0,"tid":3648595959,"ts":68137200088},{"cat":"function","dur":10,"name":"Pistachio::ConstantBuffer::Update","ph":"X","pid":0,"tid":3648595959,"ts":68137200106},{"cat":"function","dur":1,"name":"Pistachio::Shader::SetVSBuffer","ph":"X","pid":0,"tid":3648595959,"ts":68137200132},{"cat":"function","dur":2,"name":"Pistachio::RenderTexture::Bind","ph":"X","pid":0,"tid":3648595959,"ts":68137200148},{"cat":"function","dur":0,"name":"Pistachio::RenderTexture::Clear","ph":"X","pid":0,"tid":3648595959,"ts":68137200165},{"cat":"function","dur":0,"name":"Pistachio::RenderCubeMap::BindResource","ph":"X","pid":0,"tid":3648595959,"ts":68137200181},{"cat":"function","dur":1,"name":"Pistachio::VertexBuffer::Bind","ph":"X","pid":0,"tid":3648595959,"ts":68137200197},{"cat":"function","dur":0,"name":"Pistachio::IndexBuffer::Bind","ph":"X","pid":0,"tid":3648595959,"ts":68137200215},{"cat":"function","dur":0,"name":"Pistachio::RenderTexture::GetRenderTexture","ph":"X","pid":0,"tid":3648595959,"ts":68137200233},{"cat":"function","dur":0,"name":"Pistachio::RenderCubeMap::GetResource","ph":"X","pid":0,"tid":3648595959,"ts":68137200248},{"cat":"function","dur":1,"name":"Pistachio::Texture2D::CopyIntoRegion","ph":"X","pid":0,"tid":3648595959,"ts":68137200264},{"cat":"function","dur":2,"name":"Pistachio::ConstantBuffer::Update","ph":"X","pid":0,"tid":3648595959,"ts":68137200281},{"cat":"function","dur":0,"name":"Pistachio::Shader::SetVSBuffer","ph":"X","pid":0,"tid":3648595959,"ts":68137200299},{"cat":"function","dur":1,"name":"Pistachio::RenderTexture::Bind","ph":"X","pid":0,"tid":3648595959,"ts":68137200314},{"cat":"function","dur":0,"name":"Pistachio::RenderTexture::Clear","ph":"X","pid":0,"tid":3648595959,"ts":68137200331},{"cat":"function","dur":1,"name":"Pistachio::RenderCubeMap::BindResource","ph":"X","pid":0,"tid":3648595959,"ts":68137200346},{"cat":"function","dur":1,"name":"Pistachio::VertexBuffer::Bind","ph":"X","pid":0,"tid":3648595959,"ts":68137200362},{"cat":"function","dur":0,"name":"Pistachio::IndexBuffer::Bind","ph":"X","pid":0,"tid":3648595959,"ts":68137200378},{"cat":"function","dur":0,"name":"Pistachio::RenderTexture::GetRenderTexture","ph":"X","pid":0,"tid":3648595959,"ts":68137200396},{"cat":"function","dur":0,"name":"Pistachio::RenderCubeMap::GetResource","ph":"X","pid":0,"tid":3648595959,"ts":68137200412},{"cat":"function","dur":2,"name":"Pistachio::Texture2D::CopyIntoRegion","ph":"X","pid":0,"tid":3648595959,"ts":68137200427},{"cat":"function","dur":2,"name":"Pistachio::ConstantBuffer::Update","ph":"X","pid":0,"tid":3648595959,"ts":68137200444},{"cat":"function","dur":0,"name":"Pistachio::Shader::SetVSBuffer","ph":"X","pid":0,"tid":3648595959,"ts":68137200461},{"cat":"function","dur":1,"name":"Pistachio::RenderTexture::Bind","ph":"X","pid":0,"tid":3648595959,"ts":68137200477},{"cat":"function","dur":0,"name":"Pistachio::RenderTexture::Clear","ph":"X","pid":0,"tid":3648595959,"ts":68137200494},{"cat":"function","dur":0,"name":"Pistachio::RenderCubeMap::BindResource","ph":"X","pid":0,"tid":3648595959,"ts":68137200509},{"cat":"function","dur":0,"name":"Pistachio::VertexBuffer::Bind","ph":"X","pid":0,"tid":3648595959,"ts":68137200525},{"cat":"function","dur":0,"name":"Pistachio::IndexBuffer::Bind","ph":"X","pid":0,"tid":3648595959,"ts":68137200540},{"cat":"function","dur":1,"name":"Pistachio::RenderTexture::GetRenderTexture","ph":"X","pid":0,"tid":3648595959,"ts":68137200557},{"cat":"function","dur":0,"name":"Pistachio::RenderCubeMap::GetResource","ph":"X","pid":0,"tid":3648595959,"ts":68137200573},{"cat":"function","dur":2,"name":"Pistachio::Texture2D::CopyIntoRegion","ph":"X","pid":0,"tid":3648595959,"ts":68137200588},{"cat":"function","dur":1,"name":"Pistachio::ConstantBuffer::Update","ph":"X","pid":0,"tid":3648595959,"ts":68137200605},{"cat":"function","dur":1,"name":"Pistachio::Shader::SetVSBuffer","ph":"X","pid":0,"tid":3648595959,"ts":68137200622},{"cat":"function","dur":1,"name":"Pistachio::RenderTexture::Bind","ph":"X","pid":0,"tid":3648595959,"ts":68137200638},{"cat":"function","dur":1,"name":"Pistachio::RenderTexture::Clear","ph":"X","pid":0,"tid":3648595959,"ts":68137200654},{"cat":"function","dur":0,"name":"Pistachio::RenderCubeMap::BindResource","ph":"X","pid":0,"tid":3648595959,"ts":68137200670},{"cat":"function","dur":1,"name":"Pistachio::VertexBuffer::Bind","ph":"X","pid":0,"tid":3648595959,"ts":68137200685},{"cat":"function","dur":0,"name":"Pistachio::IndexBuffer::Bind","ph":"X","pid":0,"tid":3648595959,"ts":68137200701},{"cat":"function","dur":1,"name":"Pistachio::RenderTexture::GetRenderTexture","ph":"X","pid":0,"tid":3648595959,"ts":68137200718},{"cat":"function","dur":0,"name":"Pistachio::RenderCubeMap::GetResource","ph":"X","pid":0,"tid":3648595959,"ts":68137200735},{"cat":"function","dur":1,"name":"Pistachio::Texture2D::CopyIntoRegion","ph":"X","pid":0,"tid":3648595959,"ts":68137200751},{"cat":"function","dur":2,"name":"Pistachio::ConstantBuffer::Update","ph":"X","pid":0,"tid":3648595959,"ts":68137200768},{"cat":"function","dur":0,"name":"Pistachio::Shader::SetVSBuffer","ph":"X","pid":0,"tid":3648595959,"ts":68137200787},{"cat":"function","dur":2,"name":"Pistachio::RenderTexture::Bind","ph":"X","pid":0,"tid":3648595959,"ts":68137200810},{"cat":"function","dur":0,"name":"Pistachio::RenderTexture::Clear","ph":"X","pid":0,"tid":3648595959,"ts":68137200835},{"cat":"function","dur":1,"name":"Pistachio::RenderCubeMap::BindResource","ph":"X","pid":0,"tid":3648595959,"ts":68137200853},{"cat":"function","dur":1,"name":"Pistachio::VertexBuffer::Bind","ph":"X","pid":0,"tid":3648595959,"ts":68137200869},{"cat":"function","dur":0,"name":"Pistachio::IndexBuffer::Bind","ph":"X","pid":0,"tid":3648595959,"ts":68137200885},{"cat":"function","dur":0,"name":"Pistachio::RenderTexture::GetRenderTexture","ph":"X","pid":0,"tid":3648595959,"ts":68137200903},{"cat":"function","dur":0,"name":"Pistachio::RenderCubeMap::GetResource","ph":"X","pid":0,"tid":3648595959,"ts":68137200919},{"cat":"function","dur":2,"name":"Pistachio::Texture2D::CopyIntoRegion","ph":"X","pid":0,"tid":3648595959,"ts":68137200934},{"cat":"function","dur":183,"name":"Pistachio::RenderTexture::CreateStack","ph":"X","pid":0,"tid":3648595959,"ts":68137200957},{"cat":"function","dur":2,"name":"Pistachio::Shader::Bind","ph":"X","pid":0,"tid":3648595959,"ts":68137201178},{"cat":"function","dur":1,"name":"Pistachio::Shader::Bind","ph":"X","pid":0,"tid":3648595959,"ts":68137201199},{"cat":"function","dur":2,"name":"Pistachio::RenderTexture::Bind","ph":"X","pid":0,"tid":3648595959,"ts":68137201217},{"cat":"function","dur":1,"name":"Pistachio::VertexBuffer::Bind","ph":"X","pid":0,"tid":3648595959,"ts":68137201235},{"cat":"function","dur":1,"name":"Pistachio::IndexBuffer::Bind","ph":"X","pid":0,"tid":3648595959,"ts":68137201251},{"cat":"function","dur":16942,"name":"Pistachio::PixelShader::PixelShader","ph":"X","pid":0,"tid":3648595959,"ts":68137201272},{"cat":"function","dur":813,"name":"Pistachio::VertexShader::VertexShader","ph":"X","pid":0,"tid":3648595959,"ts":68137218350},{"cat":"function","dur":110,"name":"Pistachio::Shader::CreateLayout","ph":"X","pid":0,"tid":3648595959,"ts":68137219234},{"cat":"function","dur":519,"name":"Pistachio::PixelShader::PixelShader","ph":"X","pid":0,"tid":3648595959,"ts":68137219367},{"cat":"function","dur":612,"name":"Pistachio::VertexShader::VertexShader","ph":"X","pid":0,"tid":3648595959,"ts":68137219956},{"cat":"function","dur":604,"name":"Pistachio::GeometryShader::GeometryShader","ph":"X","pid":0,"tid":3648595959,"ts":68137220622},{"cat":"function","dur":108,"name":"Pistachio::Shader::CreateLayout","ph":"X","pid":0,"tid":3648595959,"ts":68137221278},{"cat":"function","dur":795,"name":"Pistachio::PixelShader::PixelShader","ph":"X","pid":0,"tid":3648595959,"ts":68137221428},{"cat":"function","dur":299,"name":"Pistachio::VertexShader::VertexShader","ph":"X","pid":0,"tid":3648595959,"ts":68137222277},{"cat":"function","dur":113,"name":"Pistachio::Shader::CreateLayout","ph":"X","pid":0,"tid":3648595959,"ts":68137222621},{"cat":"function","dur":817,"name":"Pistachio::PixelShader::PixelShader","ph":"X","pid":0,"tid":3648595959,"ts":68137222771},{"cat":"function","dur":489,"name":"Pistachio::VertexShader::VertexShader","ph":"X","pid":0,"tid":3648595959,"ts":68137223651},{"cat":"function","dur":19,"name":"Pistachio::Shader::CreateLayout","ph":"X","pid":0,"tid":3648595959,"ts":68137224186},{"cat":"function","dur":388,"name":"Pistachio::PixelShader::PixelShader","ph":"X","pid":0,"tid":3648595959,"ts":68137224226},{"cat":"function","dur":162,"name":"Pistachio::VertexShader::VertexShader","ph":"X","pid":0,"tid":3648595959,"ts":68137224660},{"cat":"function","dur":22,"name":"Pistachio::Shader::CreateLayout","ph":"X","pid":0,"tid":3648595959,"ts":68137224864},{"cat":"function","dur":13,"name":"Pistachio::ShaderLibrary::Add","ph":"X","pid":0,"tid":3648595959,"ts":68137224917},{"cat":"function","dur":6,"name":"Pistachio::ShaderLibrary::Add","ph":"X","pid":0,"tid":3648595959,"ts":68137224973},{"cat":"function","dur":3,"name":"Pistachio::ShaderLibrary::Add","ph":"X","pid":0,"tid":3648595959,"ts":68137225008},{"cat":"function","dur":3,"name":"Pistachio::ShaderLibrary::Add","ph":"X","pid":0,"tid":3648595959,"ts":68137225036},{"cat":"function","dur":3,"name":"Pistachio::ShaderLibrary::Add","ph":"X","pid":0,"tid":3648595959,"ts":68137225062},{"cat":"function","dur":412,"name":"Pistachio::Texture2D::CreateTexture","ph":"X","pid":0,"tid":3648595959,"ts":68137225088},{"cat":"function","dur":466,"name":"Pistachio::Texture2D::CreateStack","ph":"X","pid":0,"tid":3648595959,"ts":68137225088},{"cat":"function","dur":5,"name":"Pistachio::Shader::SetPSBuffer","ph":"X","pid":0,"tid":3648595959,"ts":68137225584},{"cat":"function","dur":3,"name":"Pistachio::Shader::SetVSBuffer","ph":"X","pid":0,"tid":3648595959,"ts":68137225610},{"cat":"function","dur":1,"name":"Pistachio::Shader::SetPSBuffer","ph":"X","pid":0,"tid":3648595959,"ts":68137225630},{"cat":"function","dur":2,"name":"Pistachio::RenderCubeMap::BindResource","ph":"X","pid":0,"tid":3648595959,"ts":68137225665},{"cat":"function","dur":256346,"name":"Pistachio::Renderer::Init","ph":"X","pid":0,"tid":3648595959,"ts":68136969687},{"cat":"function","dur":408,"name":"Pistachio::VertexBuffer::CreateStack","ph":"X","pid":0,"tid":3648595959,"ts":68137228491},{"cat":"function","dur":577,"name":"Pistachio::VertexBuffer::Create","ph":"X","pid":0,"tid":3648595959,"ts":68137228478},{"cat":"function","dur":719,"name":"Pistachio::IndexBuffer::CreateStack","ph":"X","pid":0,"tid":3648595959,"ts":68137229093},{"cat":"function","dur":777,"name":"Pistachio::IndexBuffer::Create","ph":"X","pid":0,"tid":3648595959,"ts":68137229092},{"cat":"function","dur":61,"name":"Pistachio::Texture2D::CreateTexture","ph":"X","pid":0,"tid":3648595959,"ts":68137229910},{"cat":"function","dur":85,"name":"Pistachio::Texture2D::CreateStack","ph":"X","pid":0,"tid":3648595959,"ts":68137229909},{"cat":"function","dur":101,"name":"Pistachio::Texture2D::Create","ph":"X","pid":0,"tid":3648595959,"ts":68137229909},{"cat":"function","dur":888,"name":"Pistachio::PixelShader::PixelShader","ph":"X","pid":0,"tid":3648595959,"ts":68137230732},{"cat":"function","dur":577,"name":"Pistachio::VertexShader::VertexShader","ph":"X","pid":0,"tid":3648595959,"ts":68137231688},{"cat":"function","dur":82,"name":"Pistachio::Shader::CreateLayout","ph":"X","pid":0,"tid":3648595959,"ts":68137232325},{"cat":"function","dur":6368,"name":"Pistachio::Renderer2D::Init","ph":"X","pid":0,"tid":3648595959,"ts":68137226075},{"cat":"function","dur":2121145,"name":"Pistachio::Application::Application","ph":"X","pid":0,"tid":3648595959,"ts":68135185871},{"cat":"function","dur":880,"name":"stbi_load","ph":"X","pid":0,"tid":3648595959,"ts":68137307087},{"cat":"function","dur":232,"name":"Pistachio::Texture2D::CreateTexture","ph":"X","pid":0,"tid":3648595959,"ts":68137307998},{"cat":"function","dur":1175,"name":"Pistachio::Texture2D::CreateStack","ph":"X","pid":0,"tid":3648595959,"ts":68137307087},{"cat":"function","dur":1194,"name":"Pistachio::Texture2D::Create","ph":"X","pid":0,"tid":3648595959,"ts":68137307086},{"cat":"function","dur":1045,"name":"stbi_load","ph":"X","pid":0,"tid":3648595959,"ts":68137308297},{"cat":"function","dur":124,"name":"Pistachio::Texture2D::CreateTexture","ph":"X","pid":0,"tid":3648595959,"ts":68137309369},{"cat":"function","dur":1224,"name":"Pistachio::Texture2D::CreateStack","ph":"X","pid":0,"tid":3648595959,"ts":68137308297},{"cat":"function","dur":1243,"name":"Pistachio::Texture2D::Create","ph":"X","pid":0,"tid":3648595959,"ts":68137308296},{"cat":"function","dur":474,"name":"stbi_load","ph":"X","pid":0,"tid":3648595959,"ts":68137309555},{"cat":"function","dur":45,"name":"Pistachio::Texture2D::CreateTexture","ph":"X","pid":0,"tid":3648595959,"ts":68137310060},{"cat":"function","dur":572,"name":"Pistachio::Texture2D::CreateStack","ph":"X","pid":0,"tid":3648595959,"ts":68137309555},{"cat":"function","dur":593,"name":"Pistachio::Texture2D::Create","ph":"X","pid":0,"tid":3648595959,"ts":68137309554},{"cat":"function","dur":1597,"name":"stbi_load","ph":"X","pid":0,"tid":3648595959,"ts":68137310164},{"cat":"function","dur":162,"name":"Pistachio::Texture2D::CreateTexture","ph":"X","pid":0,"tid":3648595959,"ts":68137311805},{"cat":"function","dur":1841,"name":"Pistachio::Texture2D::CreateStack","ph":"X","pid":0,"tid":3648595959,"ts":68137310164},{"cat":"function","dur":1867,"name":"Pistachio::Texture2D::Create","ph":"X","pid":0,"tid":3648595959,"ts":68137310164},{"cat":"function","dur":1438,"name":"stbi_load","ph":"X","pid":0,"tid":3648595959,"ts":68137312056},{"cat":"function","dur":222,"name":"Pistachio::Texture2D::CreateTexture","ph":"X","pid":0,"tid":3648595959,"ts":68137313540},{"cat":"function","dur":1802,"name":"Pistachio::Texture2D::CreateStack","ph":"X","pid":0,"tid":3648595959,"ts":68137312056},{"cat":"function","dur":1833,"name":"Pistachio::Texture2D::Create","ph":"X","pid":0,"tid":3648595959,"ts":68137312055},{"cat":"function","dur":107,"name":"Pistachio::Texture2D::CreateTexture","ph":"X","pid":0,"tid":3648595959,"ts":68137313912},{"cat":"function","dur":143,"name":"Pistachio::Texture2D::CreateStack","ph":"X","pid":0,"tid":3648595959,"ts":68137313912},{"cat":"function","dur":168,"name":"Pistachio::Texture2D::Create","ph":"X","pid":0,"tid":3648595959,"ts":68137313911},{"cat":"function","dur":871,"name":"Pistachio::PixelShader::PixelShader","ph":"X","pid":0,"tid":3648595959,"ts":68137314105},{"cat":"function","dur":363,"name":"Pistachio::VertexShader::VertexShader","ph":"X","pid":0,"tid":3648595959,"ts":68137315018},{"cat":"function","dur":2186,"name":"stbi_load","ph":"X","pid":0,"tid":3648595959,"ts":68137326975},{"cat":"function","dur":651,"name":"Pistachio::Texture2D::CreateTexture","ph":"X","pid":0,"tid":3648595959,"ts":68137329243},{"cat":"function","dur":2975,"name":"Pistachio::Texture2D::CreateStack","ph":"X","pid":0,"tid":3648595959,"ts":68137326975},{"cat":"function","dur":2993,"name":"Pistachio::Texture2D::Create","ph":"X","pid":0,"tid":3648595959,"ts":68137326974},{"cat":"function","dur":1745,"name":"stbi_load","ph":"X","pid":0,"tid":3648595959,"ts":68137329986},{"cat":"function","dur":446,"name":"Pistachio::Texture2D::CreateTexture","ph":"X","pid":0,"tid":3648595959,"ts":68137331774},{"cat":"function","dur":2277,"name":"Pistachio::Texture2D::CreateStack","ph":"X","pid":0,"tid":3648595959,"ts":68137329986},{"cat":"function","dur":2299,"name":"Pistachio::Texture2D::Create","ph":"X","pid":0,"tid":3648595959,"ts":68137329986},{"cat":"function","dur":1442,"name":"stbi_load","ph":"X","pid":0,"tid":3648595959,"ts":68137332306},{"cat":"function","dur":410,"name":"Pistachio::Texture2D::CreateTexture","ph":"X","pid":0,"tid":3648595959,"ts":68137333780},{"cat":"function","dur":1926,"name":"Pistachio::Texture2D::CreateStack","ph":"X","pid":0,"tid":3648595959,"ts":68137332306},{"cat":"function","dur":1945,"name":"Pistachio::Texture2D::Create","ph":"X","pid":0,"tid":3648595959,"ts":68137332304},{"cat":"function","dur":1110,"name":"stbi_load","ph":"X","pid":0,"tid":3648595959,"ts":68137334266},{"cat":"function","dur":42,"name":"Pistachio::Texture2D::CreateTexture","ph":"X","pid":0,"tid":3648595959,"ts":68137335405},{"cat":"function","dur":1203,"name":"Pistachio::Texture2D::CreateStack","ph":"X","pid":0,"tid":3648595959,"ts":68137334266},{"cat":"function","dur":1219,"name":"Pistachio::Texture2D::Create","ph":"X","pid":0,"tid":3648595959,"ts":68137334265},{"cat":"function","dur":2313,"name":"stbi_load","ph":"X","pid":0,"tid":3648595959,"ts":68137335502},{"cat":"function","dur":388,"name":"Pistachio::Texture2D::CreateTexture","ph":"X","pid":0,"tid":3648595959,"ts":68137337844},{"cat":"function","dur":2770,"name":"Pistachio::Texture2D::CreateStack","ph":"X","pid":0,"tid":3648595959,"ts":68137335501},{"cat":"function","dur":2786,"name":"Pistachio::Texture2D::Create","ph":"X","pid":0,"tid":3648595959,"ts":68137335501},{"cat":"function","dur":76,"name":"Pistachio::VertexBuffer::CreateStack","ph":"X","pid":0,"tid":3648595959,"ts":68137356988},{"cat":"function","dur":14,"name":"Pistachio::IndexBuffer::CreateStack","ph":"X","pid":0,"tid":3648595959,"ts":68137357137},{"cat":"function","dur":17733,"name":"Pistachio::Mesh::CreateStack","ph":"X","pid":0,"tid":3648595959,"ts":68137339607},{"cat":"function","dur":75,"name":"Pistachio::Shader::CreateLayout","ph":"X","pid":0,"tid":3648595959,"ts":68137357366},{"cat":"function","dur":1083,"name":"Pistachio::RenderTexture::CreateStack","ph":"X","pid":0,"tid":3648595959,"ts":68137364733},{"cat":"function","dur":200,"name":"Pistachio::RenderTexture::CreateStack","ph":"X","pid":0,"tid":3648595959,"ts":68137365901},{"cat":"function","dur":37,"name":"Pistachio::VertexBuffer::CreateStack","ph":"X","pid":0,"tid":3648595959,"ts":68137366915},{"cat":"function","dur":16,"name":"Pistachio::IndexBuffer::CreateStack","ph":"X","pid":0,"tid":3648595959,"ts":68137366995},{"cat":"function","dur":722,"name":"Pistachio::Mesh::Mesh","ph":"X","pid":0,"tid":3648595959,"ts":68137366309},{"cat":"function","dur":8197,"name":"Pistachio::Scene::Scene","ph":"X","pid":0,"tid":3648595959,"ts":68137358855},{"cat":"function","dur":79,"name":"Pistachio::VertexBuffer::CreateStack","ph":"X","pid":0,"tid":3648595959,"ts":68137388392},{"cat":"function","dur":12,"name":"Pistachio::IndexBuffer::CreateStack","ph":"X","pid":0,"tid":3648595959,"ts":68137388542},{"cat":"function","dur":21517,"name":"Pistachio::Mesh::CreateStack","ph":"X","pid":0,"tid":3648595959,"ts":68137367215},{"cat":"function","dur":21540,"name":"Pistachio::Mesh::Create","ph":"X","pid":0,"tid":3648595959,"ts":68137367214},{"cat":"function","dur":17,"name":"Pistachio::ConstantBuffer::Create","ph":"X","pid":0,"tid":3648595959,"ts":68137388776},{"cat":"function","dur":594,"name":"Pistachio::VertexBuffer::CreateStack","ph":"X","pid":0,"tid":3648595959,"ts":68137705133},{"cat":"function","dur":97,"name":"Pistachio::IndexBuffer::CreateStack","ph":"X","pid":0,"tid":3648595959,"ts":68137705822},{"cat":"function","dur":318468,"name":"Pistachio::Mesh::CreateStack","ph":"X","pid":0,"tid":3648595959,"ts":68137388874},{"cat":"function","dur":318508,"name":"Pistachio::Mesh::Create","ph":"X","pid":0,"tid":3648595959,"ts":68137388872},{"cat":"function","dur":24,"name":"Pistachio::ConstantBuffer::Create","ph":"X","pid":0,"tid":3648595959,"ts":68137707403}]}